{
  "project_info": {
    "project_number": "345784452202",
    "project_id": "thesportk",
    "storage_bucket": "thesportk.appspot.com"
  },
  "client": [
    {
      "client_info": {
        "mobilesdk_app_id": "1:345784452202:android:8a07fad1d5bd50d550f613",
        "android_client_info": {
          "package_name": "com.sportk.wecan"
        }
      },
      "oauth_client": [
        {
          "client_id": "345784452202-20ajjtpjcaa06q0fd2uarfhcvrkh2sbm.apps.googleusercontent.com",
          "client_type": 3
        }
      ],
      "api_key": [
        {
          "current_key": "AIzaSyADxL_T3H9VmZoTV6f-tFKH2dkuX7w7Nso"
        }
      ],
      "services": {
        "appinvite_service": {
          "other_platform_oauth_client": [
            {
              "client_id": "345784452202-20ajjtpjcaa06q0fd2uarfhcvrkh2sbm.apps.googleusercontent.com",
              "client_type": 3
            }
          ]
        }
      }
    }
  ],
  "configuration_version": "1"
}